ue_schedule/__init__.py
ue_schedule/cli.py
ue_schedule/event.py
ue_schedule/exceptions.py
ue_schedule/schedule.py
ue_schedule-2.2.0.post1.dist-info/entry_points.txt
ue_schedule-2.2.0.post1.dist-info/LICENSE
ue_schedule-2.2.0.post1.dist-info/WHEEL
ue_schedule-2.2.0.post1.dist-info/METADATA
ue_schedule-2.2.0.post1.dist-info/RECORD
