Metadata-Version: 2.1
Name: ue-schedule
Version: 2.2.0.post1
Summary: UE Katowice class schedule utility library
Home-page: https://github.com/rimmaciej/ue-schedule.git
License: MIT
Keywords: class-schedule,university,ue-katowice
Author: Maciej Rim
Author-email: maciej.rim@gmail.com
Requires-Python: >=3.6.2,<4.0.0
Classifier: License :: OSI Approved :: MIT License
Classifier: Programming Language :: Python :: 3
Classifier: Programming Language :: Python :: 3.7
Classifier: Programming Language :: Python :: 3.8
Classifier: Programming Language :: Python :: 3.9
Requires-Dist: click (>=7.1.2,<8.0.0)
Requires-Dist: icalendar (>=4.0.7,<5.0.0)
Requires-Dist: requests (>=2.24.0,<3.0.0)
Project-URL: Repository, https://github.com/rimmaciej/ue-schedule.git
